{
    "total": 1,
    "data": [
        {
            "season_slug_title": "jujutsu-kaisen-0",
            "sequence_number": 0,
            "is_premium_only": true,
            "season_sequence_number": 2,
            "is_mature": false,
            "episode_number": null,
            "is_clip": false,
            "subtitle_locales": [
                "en-US",
                "es-419",
                "es-ES",
                "fr-FR",
                "pt-BR",
                "pt-PT",
                "ar-SA",
                "it-IT",
                "de-DE",
                "ru-RU"
            ],
            "episode_air_date": "2022-09-21T00:00:00+09:00",
            "versions": [
                {
                    "audio_locale": "ja-JP",
                    "guid": "G4VUQ9ZQ3",
                    "is_premium_only": true,
                    "media_guid": "GNJFDEGDZ",
                    "original": true,
                    "roles": [
                        "main"
                    ],
                    "season_guid": "G6DQCGD78",
                    "variant": ""
                },
                {
                    "audio_locale": "es-419",
                    "guid": "G14U4D24X",
                    "is_premium_only": true,
                    "media_guid": "GKKF3JQ38",
                    "original": false,
                    "roles": [
                        "dub"
                    ],
                    "season_guid": "GYQ4CZ7WV",
                    "variant": ""
                },
                {
                    "audio_locale": "pt-BR",
                    "guid": "GJWU2382X",
                    "is_premium_only": true,
                    "media_guid": "GM8FX2WX4",
                    "original": false,
                    "roles": [
                        "dub"
                    ],
                    "season_guid": "GY5VCDWGV",
                    "variant": ""
                },
                {
                    "audio_locale": "fr-FR",
                    "guid": "GN7UDEGDG",
                    "is_premium_only": true,
                    "media_guid": "GVMF0EJ0J",
                    "original": false,
                    "roles": [
                        "dub"
                    ],
                    "season_guid": "GRWEC3G02",
                    "variant": ""
                },
                {
                    "audio_locale": "de-DE",
                    "guid": "GK9U3JQ35",
                    "is_premium_only": true,
                    "media_guid": "G3WFX1QX0",
                    "original": false,
                    "roles": [
                        "dub"
                    ],
                    "season_guid": "GRGGCV0PW",
                    "variant": ""
                },
                {
                    "audio_locale": "ru-RU",
                    "guid": "GMKUX2WX7",
                    "is_premium_only": true,
                    "media_guid": "GPPFK7EK4",
                    "original": false,
                    "roles": [
                        "dub"
                    ],
                    "season_guid": "G609CX4EW",
                    "variant": ""
                },
                {
                    "audio_locale": "it-IT",
                    "guid": "GVWU0EJ0E",
                    "is_premium_only": true,
                    "media_guid": "G25F0KJ0K",
                    "original": false,
                    "roles": [
                        "dub"
                    ],
                    "season_guid": "GRE5CQKVQ",
                    "variant": ""
                },
                {
                    "audio_locale": "es-ES",
                    "guid": "G31UX1QXG",
                    "is_premium_only": true,
                    "media_guid": "G8MFNXENZ",
                    "original": false,
                    "roles": [
                        "dub"
                    ],
                    "season_guid": "G675CD0N4",
                    "variant": ""
                },
                {
                    "audio_locale": "en-US",
                    "guid": "GPWUK7EKG",
                    "is_premium_only": true,
                    "media_guid": "GZ4FVKJV4",
                    "original": false,
                    "roles": [
                        "dub"
                    ],
                    "season_guid": "G69PC27V9",
                    "variant": ""
                }
            ],
            "premium_available_date": "2022-09-21T08:00:00Z",
            "identifier": "GRDV0019R|M|E0",
            "available_date": null,
            "eligible_region": "CL",
            "description": "Cuando apenas eran unos niños, Rika Orimoto murió en un accidente de tráfico justo ante los ojos de su buen amigo Yuka Okkotsu.\r\n\r\n“Es una promesa. Cuando seamos grandes, nos casaremos”.\r\n\r\nRika se convirtió en un espíritu y Yuta llegó a desear su propia muerte tras sufrir su maldición, pero el gran hechicero Satoru Gojo le dio la bienvenida a la Academia de Hechicería.\r\n\r\nAllí Yuta conoce a sus compañeros: Maki Zen’in, Toge Inumaki y Panda, y por fin encuentra la determinación que le faltaba.\r\n\r\n“¡Por fin tengo la confianza para decir que no es malo que siga viviendo!”.\r\n\r\n“Estando en la Academia de Hechicería podré romper la maldición de Rika”.\r\n\r\nMientras tanto, el malvado usuario de maldiciones Suguru Geto, quien fue expulsado de la academia de hechicería por asesinar a inocentes, aparece ante Yuta y el resto.\r\n\r\n“El próximo 24 de diciembre celebraremos el Desfile Nocturno de los Cien Demonios”.\r\n\r\nGeto aspira a crear un paraíso exclusivo para hechiceros y decide liberar miles de maldiciones en Shinjuku y Kyoto para exterminar a todos los que no son hechiceros.\r\n\r\n¿Podrá Yuta detener a Geto?\r\n\r\n¿Y qué ocurrirá con lo de romper la maldición de Rika?",
            "mature_blocked": false,
            "availability_status": "available",
            "slug_title": "jujutsu-kaisen-0",
            "availability_starts": "2022-09-21T08:00:00Z",
            "recent_variant": "",
            "extended_maturity_rating": {
                "level": "M2",
                "rating": "16",
                "system": "cr-tv"
            },
            "closed_captions_available": false,
            "episode": "",
            "duration_ms": 6295389,
            "season_title": "[JAP] JUJUTSU KAISEN 0",
            "recent_audio_locale": "ja-JP",
            "media_type": "episode",
            "availability_ends": "9998-11-30T08:00:00Z",
            "production_episode_id": "",
            "title": "JUJUTSU KAISEN 0",
            "season_id": "G6DQCGD78",
            "streams_link": "/content/v2/cms/videos/GNJFDEGDZ/streams",
            "season_display_number": "",
            "slug": "",
            "seo_title": "",
            "season_tags": [],
            "roles": [
                "main"
            ],
            "next_episode_id": "G0DUNJ2JP",
            "availability_notes": "",
            "listing_id": "",
            "series_title": "JUJUTSU KAISEN",
            "images": {
                "thumbnail": [
                    [
                        {
                            "height": 180,
                            "source": "https://www.crunchyroll.com/imgsrv/display/thumbnail/320x180/catalog/crunchyroll/72e7b52fe56626a471f32126bef57ee6.jpg",
                            "type": "thumbnail",
                            "width": 320
                        },
                        {
                            "height": 338,
                            "source": "https://www.crunchyroll.com/imgsrv/display/thumbnail/600x338/catalog/crunchyroll/72e7b52fe56626a471f32126bef57ee6.jpg",
                            "type": "thumbnail",
                            "width": 600
                        },
                        {
                            "height": 360,
                            "source": "https://www.crunchyroll.com/imgsrv/display/thumbnail/640x360/catalog/crunchyroll/72e7b52fe56626a471f32126bef57ee6.jpg",
                            "type": "thumbnail",
                            "width": 640
                        },
                        {
                            "height": 450,
                            "source": "https://www.crunchyroll.com/imgsrv/display/thumbnail/800x450/catalog/crunchyroll/72e7b52fe56626a471f32126bef57ee6.jpg",
                            "type": "thumbnail",
                            "width": 800
                        },
                        {
                            "height": 675,
                            "source": "https://www.crunchyroll.com/imgsrv/display/thumbnail/1200x675/catalog/crunchyroll/72e7b52fe56626a471f32126bef57ee6.jpg",
                            "type": "thumbnail",
                            "width": 1200
                        },
                        {
                            "height": 810,
                            "source": "https://www.crunchyroll.com/imgsrv/display/thumbnail/1440x810/catalog/crunchyroll/72e7b52fe56626a471f32126bef57ee6.jpg",
                            "type": "thumbnail",
                            "width": 1440
                        },
                        {
                            "height": 900,
                            "source": "https://www.crunchyroll.com/imgsrv/display/thumbnail/1600x900/catalog/crunchyroll/72e7b52fe56626a471f32126bef57ee6.jpg",
                            "type": "thumbnail",
                            "width": 1600
                        },
                        {
                            "height": 1080,
                            "source": "https://www.crunchyroll.com/imgsrv/display/thumbnail/1920x1080/catalog/crunchyroll/72e7b52fe56626a471f32126bef57ee6.jpg",
                            "type": "thumbnail",
                            "width": 1920
                        }
                    ]
                ]
            },
            "maturity_ratings": [
                "TV-14"
            ],
            "premium_date": null,
            "channel_id": "crunchyroll",
            "season_number": 44,
            "is_dubbed": true,
            "series_slug_title": "jujutsu-kaisen",
            "available_offline": true,
            "hd_flag": true,
            "free_available_date": "9998-11-30T08:00:00Z",
            "is_subbed": true,
            "series_id": "GRDV0019R",
            "audio_locale": "ja-JP",
            "content_descriptors": [
                "Desnudez",
                "Lenguaje ofensivo",
                "Tabaquismo",
                "Violencia"
            ],
            "id": "G4VUQ9ZQ3",
            "upload_date": "2022-09-21T00:00:00+09:00",
            "seo_description": "",
            "next_episode_title": "El tesoro escondido"
        }
    ],
    "meta": {
        "versions_considered": true
    }
}